{
	"Changes": [
		{
			"LogName": "Gift Taste",
			"Action": "EditData",
			"Target": "Data/NPCGiftTastes",
			"TextOperations": [
				{
					"Operation": "Append",
					"Target": [
						"Fields",
						"Abigail",
						1
					],
					"Value": "{{ModID}}_BabyBooSquash",
					"Delimiter": " "
				},
				{
					"Operation": "Append",
					"Target": [
						"Fields",
						"Alex",
						1
					],
					"Value": "{{ModID}}_Iris",
					"Delimiter": " "
				},
				{
					"Operation": "Append",
					"Target": [
						"Fields",
						"Caroline",
						1
					],
					"Value": "{{ModID}}_ButterflyLavender {{ModID}}_WinterIris",
					"Delimiter": " "
				},
				{
					"Operation": "Append",
					"Target": [
						"Fields",
						"Clint",
						1
					],
					"Value": "{{ModID}}_Snowdrop",
					"Delimiter": " "
				},
				{
					"Operation": "Append",
					"Target": [
						"Fields",
						"Demetrius",
						1
					],
					"Value": "{{ModID}}_BlueFlame",
					"Delimiter": " "
				},
				{
					"Operation": "Append",
					"Target": [
						"Fields",
						"Dwarf",
						1
					],
					"Value": "{{ModID}}_Foxglove",
					"Delimiter": " "
				},
				{
					"Operation": "Append",
					"Target": [
						"Fields",
						"Emily",
						1
					],
					"Value": "{{ModID}}_ForgetMeNot",
					"Delimiter": " "
				},
				{
					"Operation": "Append",
					"Target": [
						"Fields",
						"George",
						1
					],
					"Value": "{{ModID}}_Hollyhock",
					"Delimiter": " "
				},
				{
					"Operation": "Append",
					"Target": [
						"Fields",
						"Gus",
						1
					],
					"Value": "{{ModID}}_Borage",
					"Delimiter": " "
				},
				{
					"Operation": "Append",
					"Target": [
						"Fields",
						"Haley",
						1
					],
					"Value": "{{ModID}}_SpringBells {{ModID}}_Calendula",
					"Delimiter": " "
				},
				{
					"Operation": "Append",
					"Target": [
						"Fields",
						"Harvey",
						1
					],
					"Value": "{{ModID}}_Calendula",
					"Delimiter": " "
				},
				{
					"Operation": "Append",
					"Target": [
						"Fields",
						"Harvey",
						3 //Like
					],
					"Value": "{{ModID}}_Foxglove",
					"Delimiter": " "
				},
				{
					"Operation": "Append",
					"Target": [
						"Fields",
						"Jas",
						1
					],
					"Value": "{{ModID}}_SpringPansy",
					"Delimiter": " "
				},
				{
					"Operation": "Append",
					"Target": [
						"Fields",
						"Jas",
						5 //Dislike
					],
					"Value": "{{ModID}}_Borage",
					"Delimiter": " "
				},
				{
					"Operation": "Append",
					"Target": [
						"Fields",
						"Jas",
						7 //Hate
					],
					"Value": "{{ModID}}_Foxglove",
					"Delimiter": " "
				},
				{
					"Operation": "Append",
					"Target": [
						"Fields",
						"Jodi",
						1
					],
					"Value": "{{ModID}}_Clematis",
					"Delimiter": " "
				},
				{
					"Operation": "Append",
					"Target": [
						"Fields",
						"Kent",
						1
					],
					"Value": "{{ModID}}_WinterPansy",
					"Delimiter": " "
				},
				{
					"Operation": "Append",
					"Target": [
						"Fields",
						"Kent",
						7 //Hate
					],
					"Value": "{{ModID}}_Cornflower",
					"Delimiter": " "
				},
				{
					"Operation": "Append",
					"Target": [
						"Fields",
						"Krobus",
						1
					],
					"Value": "{{ModID}}_BabyBooSquash {{ModID}}_Foxglove",
					"Delimiter": " "
				},
				{
					"Operation": "Append",
					"Target": [
						"Fields",
						"Leah",
						1
					],
					"Value": "{{ModID}}_Borage {{ModID}}_TallMallow",
					"Delimiter": " "
				},
				{
					"Operation": "Append",
					"Target": [
						"Fields",
						"Lewis",
						1
					],
					"Value": "{{ModID}}_Hollyhock",
					"Delimiter": " "
				},
				{
					"Operation": "Append",
					"Target": [
						"Fields",
						"Linus",
						1
					],
					"Value": "{{ModID}}_Snowdrop {{ModID}}_Clematis",
					"Delimiter": " "
				},
				{
					"Operation": "Append",
					"Target": [
						"Fields",
						"Maru",
						1
					],
					"Value": "{{ModID}}_ForgetMeNot {{ModID}}_RomanescoCabbage",
					"Delimiter": " "
				},
				{
					"Operation": "Append",
					"Target": [
						"Fields",
						"Pam",
						1
					],
					"Value": "{{ModID}}_SpringBells",
					"Delimiter": " "
				},
				{
					"Operation": "Append",
					"Target": [
						"Fields",
						"Penny",
						1
					],
					"Value": "{{ModID}}_Cornflower",
					"Delimiter": " "
				},
				{
					"Operation": "Append",
					"Target": [
						"Fields",
						"Pierre",
						1
					],
					"Value": "{{ModID}}_ButterflyLavender",
					"Delimiter": " "
				},
				{
					"Operation": "Append",
					"Target": [
						"Fields",
						"Robin",
						1
					],
					"Value": "{{ModID}}_TallMallow",
					"Delimiter": " "
				},
				{
					"Operation": "Append",
					"Target": [
						"Fields",
						"Sam",
						1
					],
					"Value": "{{ModID}}_WinterIris",
					"Delimiter": " "
				},
				{
					"Operation": "Append",
					"Target": [
						"Fields",
						"Sam",
						5 //Dislike
					],
					"Value": "{{ModID}}_BabyBooSquash",
					"Delimiter": " "
				},
				{
					"Operation": "Append",
					"Target": [
						"Fields",
						"Sandy",
						1
					],
					"Value": "{{ModID}}_ButterflyLavender {{ModID}}_SpringPansy",
					"Delimiter": " "
				},
				{
					"Operation": "Append",
					"Target": [
						"Fields",
						"Sebastian",
						1
					],
					"Value": "{{ModID}}_BlueFlame",
					"Delimiter": " "
				},
				{
					"Operation": "Append",
					"Target": [
						"Fields",
						"Vincent",
						1
					],
					"Value": "{{ModID}}_PurpleFlame",
					"Delimiter": " "
				},
				{
					"Operation": "Append",
					"Target": [
						"Fields",
						"Vincent",
						5 //Dislike
					],
					"Value": "{{ModID}}_BabyBooSquash {{ModID}}_Borage",
					"Delimiter": " "
				},
				{
					"Operation": "Append",
					"Target": [
						"Fields",
						"Vincent",
						7 //Hate
					],
					"Value": "{{ModID}}_Foxglove",
					"Delimiter": " "
				},
				{
					"Operation": "Append",
					"Target": [
						"Fields",
						"Wizard",
						1
					],
					"Value": "{{ModID}}_BabyBooSquash {{ModID}}_PurpleFlame",
					"Delimiter": " "
				},
			]
		},
		{
			"LogName": "Abigail Dialogue Gift Taste",
			"Action": "EditData",
			"Target": "Characters/Dialogue/Abigail",
			"Entries": {
				"AcceptGift_(O){{ModID}}_BabyBooSquash": "{{i18n: SereneMeadowAbigailDialogueAcceptGift_(O){{ModID}}_BabyBooSquash{{Random:R01, R02}}}}",
			},
		},
		{
			"LogName": "Alex Dialogue Gift Taste",
			"Action": "EditData",
			"Target": "Characters/Dialogue/Alex",
			"Entries": {
				"AcceptGift_(O){{ModID}}_Iris": "{{i18n: SereneMeadowAlexDialogueAcceptGift_(O){{ModID}}_Iris{{Random:R01, R02}}}}",
			},
		},
		{
			"LogName": "Caroline Dialogue Gift Taste",
			"Action": "EditData",
			"Target": "Characters/Dialogue/Caroline",
			"Entries": {
				"AcceptGift_(O){{ModID}}_ButterflyLavender": "{{i18n: SereneMeadowCarolineDialogueAcceptGift_(O){{ModID}}_ButterflyLavender{{Random:R01, R02}}}}",
			},
		},
		{
			"LogName": "Clint Dialogue Gift Taste",
			"Action": "EditData",
			"Target": "Characters/Dialogue/Clint",
			"Entries": {
				"AcceptGift_(O){{ModID}}_Snowdrop": "{{i18n: SereneMeadowClintDialogueAcceptGift_(O){{ModID}}_Snowdrop}}",
			},
		},
		{
			"LogName": "Demetrius Dialogue Gift Taste",
			"Action": "EditData",
			"Target": "Characters/Dialogue/Demetrius",
			"Entries": {
				"AcceptGift_(O){{ModID}}_BlueFlame": "{{i18n: SereneMeadowDemetriusDialogueAcceptGift_(O){{ModID}}_BlueFlame{{Random:R01, R02}}}}",
			},
		},
		{
			"LogName": "Emily Dialogue Gift Taste",
			"Action": "EditData",
			"Target": "Characters/Dialogue/Emily",
			"Entries": {
				"AcceptGift_(O){{ModID}}_ForgetMeNot": "{{i18n: SereneMeadowEmilyDialogueAcceptGift_(O){{ModID}}_ForgetMeNot}}",
			},
		},
		{
			"LogName": "Evelyn Dialogue Gift Taste",
			"Action": "EditData",
			"Target": "Characters/Dialogue/Evelyn",
			"Entries": {
				"AcceptGift_(O){{ModID}}_SpringPansy": "{{i18n: SereneMeadowEvelynDialogueAcceptGift_(O){{ModID}}_SpringPansy}}",
			},
		},
		{
			"LogName": "George Dialogue Gift Taste",
			"Action": "EditData",
			"Target": "Characters/Dialogue/George",
			"Entries": {
				"AcceptGift_(O){{ModID}}_Hollyhock": "{{i18n: SereneMeadowGeorgeDialogueAcceptGift_(O){{ModID}}_Hollyhock}}",
			},
		},
		{
			"LogName": "Gus Dialogue Gift Taste",
			"Action": "EditData",
			"Target": "Characters/Dialogue/Gus",
			"Entries": {
				"AcceptGift_(O){{ModID}}_Borage": "{{i18n: SereneMeadowGusDialogueAcceptGift_(O){{ModID}}_Borage}}",
			},
		},
		{
			"LogName": "Haley Dialogue Gift Taste",
			"Action": "EditData",
			"Target": "Characters/Dialogue/Haley",
			"Entries": {
				"AcceptGift_(O){{ModID}}_SpringBells": "{{i18n: SereneMeadowHaleyDialogueAcceptGift_(O){{ModID}}_SpringBells}}",
				"AcceptGift_(O){{ModID}}_Calendula": "{{i18n: SereneMeadowHaleyDialogueAcceptGift_(O){{ModID}}_Calendula}}",
			},
		},
		{
			"LogName": "Harvey Dialogue Gift Taste",
			"Action": "EditData",
			"Target": "Characters/Dialogue/Harvey",
			"Entries": {
				"AcceptGift_(O){{ModID}}_Calendula": "{{i18n: SereneMeadowHarveyDialogueAcceptGift_(O){{ModID}}_Calendula}}",
				"AcceptGift_(O){{ModID}}_Foxglove": "{{i18n: SereneMeadowHarveyDialogueAcceptGift_(O){{ModID}}_Foxglove}}",
			},
		},
		{
			"LogName": "Jas Dialogue Gift Taste",
			"Action": "EditData",
			"Target": "Characters/Dialogue/Jas",
			"Entries": {
				"AcceptGift_(O){{ModID}}_SpringPansy": "{{i18n: SereneMeadowJasDialogueAcceptGift_(O){{ModID}}_SpringPansy}}",
				"AcceptGift_(O){{ModID}}_PurpleFlame": "{{i18n: SereneMeadowJasDialogueAcceptGift_(O){{ModID}}_PurpleFlame}}",
				"AcceptGift_(O){{ModID}}_Foxglove": "{{i18n: SereneMeadowJasDialogueAcceptGift_(O){{ModID}}_Foxglove}}",
			},
		},
		{
			"LogName": "Pam Dialogue Gift Taste",
			"Action": "EditData",
			"Target": "Characters/Dialogue/Pam",
			"Entries": {
				"AcceptGift_(O){{ModID}}_SpringBells": "{{i18n: SereneMeadowPamDialogueAcceptGift_(O){{ModID}}_SpringBells}}",
			},
		},
		{
			"LogName": "Pierre Dialogue Gift Taste",
			"Action": "EditData",
			"Target": "Characters/Dialogue/Pierre",
			"Entries": {
				"AcceptGift_(O){{ModID}}_ButterflyLavender": "{{i18n: SereneMeadowPierreDialogueAcceptGift_(O){{ModID}}_ButterflyLavender}}",
			},
		},
		{
			"LogName": "Robin Dialogue Gift Taste",
			"Action": "EditData",
			"Target": "Characters/Dialogue/Robin",
			"Entries": {
				"AcceptGift_(O){{ModID}}_BlueFlame": "{{i18n: SereneMeadowRobinDialogueAcceptGift_(O){{ModID}}_BlueFlame{{Random:R01, R02}}}}",
			},
		},
		{
			"LogName": "Sam Dialogue Gift Taste",
			"Action": "EditData",
			"Target": "Characters/Dialogue/Sam",
			"Entries": {
				"AcceptGift_(O){{ModID}}_BabyBooSquash": "{{i18n: SereneMeadowSamDialogueAcceptGift_(O){{ModID}}_BabyBooSquash}}",
			},
		},
		{
			"LogName": "Sebastian Dialogue Gift Taste",
			"Action": "EditData",
			"Target": "Characters/Dialogue/Sebastian",
			"Entries": {
				"AcceptGift_(O){{ModID}}_BlueFlame": "{{i18n: SereneMeadowSebastianDialogueAcceptGift_(O){{ModID}}_BlueFlame{{Random:R01, R02}}}}",
			},
		},
		/*
		{
			"LogName": "TODO Dialogue Gift Taste",
			"Action": "EditData",
			"Target": "Characters/Dialogue/TODO",
			"Entries": {
				"AcceptGift_(O){{ModID}}_CADEAU": "{{i18n: SereneMeadowTODODialogueAcceptGift_(O){{ModID}}_CADEAU}}",
			},
		},
		*/
	]
}